README.md
randstr.py
setup.py
randstr_random.egg-info/PKG-INFO
randstr_random.egg-info/SOURCES.txt
randstr_random.egg-info/dependency_links.txt
randstr_random.egg-info/top_level.txt