Metadata-Version: 2.1
Name: randstr-random
Version: 1.1.2
Summary: Python package for generating strings with random characters.
Home-page: https://github.com/CodeConfidant/randstr-random
Author: Drew Hainer
Author-email: codeconfidant@gmail.com
License: MIT
Platform: Windows
Platform: Linux
